cazy_parser/__init__.py
cazy_parser/cli.py
cazy_parser/modules/__init__.py
cazy_parser/modules/fasta.py
cazy_parser/modules/html.py
cazy_parser/utils.py
cazy_parser/version.py
cazy_parser-2.0.3.dist-info/LICENSE
cazy_parser-2.0.3.dist-info/METADATA
cazy_parser-2.0.3.dist-info/WHEEL
cazy_parser-2.0.3.dist-info/entry_points.txt
cazy_parser-2.0.3.dist-info/RECORD
