Metadata-Version: 2.1
Name: cazy-parser
Version: 2.0.3
Summary: A way to extract specific information from CAZy
License: GPLv3
Keywords: cazy,database,datamining
Author: Rodrigo V. Honorato
Author-email: rvhonorato@protonmail.com
Requires-Python: >=3.9,<4.0
Classifier: Development Status :: 5 - Production/Stable
Classifier: Intended Audience :: Science/Research
Classifier: License :: OSI Approved :: GNU General Public License v3 (GPLv3)
Classifier: License :: Other/Proprietary License
Classifier: Programming Language :: Python :: 3
Classifier: Programming Language :: Python :: 3.9
Classifier: Programming Language :: Python :: 3.10
Classifier: Programming Language :: Python :: 3.11
Classifier: Topic :: Scientific/Engineering :: Bio-Informatics
Requires-Dist: beautifulsoup4 (>=4.11.1,<5.0.0)
Requires-Dist: biopython (>=1.81,<2.0)
Requires-Dist: progressbar2 (>=4.2.0,<5.0.0)
Requires-Dist: requests (>=2.27.1,<3.0.0)
